Metadata-Version: 2.1
Name: PyDither
Version: 0.0.1
Summary: python - image dithering
Home-page: https://github.com/Utkarsh-Deshmukh/image-dithering-python
Author: utkarsh-deshmukh
Author-email: utkarsh.deshmukh@gmail.com
License: MIT
Download-URL: https://github.com/Utkarsh-Deshmukh/image-dithering-python/archive/main.zip
Keywords: image dithering
Platform: UNKNOWN
Classifier: Programming Language :: Python :: 3
Classifier: License :: OSI Approved :: MIT License
Classifier: Operating System :: OS Independent
